odoo/addons/account_tax_one_vat_purchase/README.rst
odoo/addons/account_tax_one_vat_purchase/__init__.py
odoo/addons/account_tax_one_vat_purchase/__manifest__.py
odoo/addons/account_tax_one_vat_purchase/i18n/account_tax_one_vat_purchase.pot
odoo/addons/account_tax_one_vat_purchase/i18n/it.po
odoo/addons/account_tax_one_vat_purchase/models/__init__.py
odoo/addons/account_tax_one_vat_purchase/models/purchase_order_line.py
odoo/addons/account_tax_one_vat_purchase/readme/CONTRIBUTORS.rst
odoo/addons/account_tax_one_vat_purchase/readme/DESCRIPTION.rst
odoo/addons/account_tax_one_vat_purchase/static/description/icon.png
odoo/addons/account_tax_one_vat_purchase/static/description/index.html
odoo/addons/account_tax_one_vat_purchase/tests/__init__.py
odoo/addons/account_tax_one_vat_purchase/tests/test_account_tax_one_vat_purchase.py
odoo_addon_account_tax_one_vat_purchase-16.0.1.0.0.4.dist-info/METADATA
odoo_addon_account_tax_one_vat_purchase-16.0.1.0.0.4.dist-info/WHEEL
odoo_addon_account_tax_one_vat_purchase-16.0.1.0.0.4.dist-info/top_level.txt
odoo_addon_account_tax_one_vat_purchase-16.0.1.0.0.4.dist-info/RECORD
